kwimage_ext/__init__.py
kwimage_ext/algo/__init__.py
kwimage_ext/algo/algo_nms.py
kwimage_ext/algo/_nms_backend/__init__.py
kwimage_ext/algo/_nms_backend/cpu_nms.cpython-310-x86_64-linux-gnu.so
kwimage_ext/algo/_nms_backend/cpu_soft_nms.cpython-310-x86_64-linux-gnu.so
kwimage_ext/algo/_nms_backend/gpu_nms.cpython-310-x86_64-linux-gnu.so
kwimage_ext/algo/_nms_backend/py_nms.py
kwimage_ext/algo/_nms_backend/torch_nms.py
kwimage_ext/structs/__init__.py
kwimage_ext/structs/_boxes_backend/__init__.py
kwimage_ext/structs/_boxes_backend/cython_boxes.cpython-310-x86_64-linux-gnu.so
kwimage_ext/structs/_mask_backend/__init__.py
kwimage_ext/structs/_mask_backend/cython_mask.cpython-310-x86_64-linux-gnu.so
kwimage_ext-0.3.1.dist-info/METADATA
kwimage_ext-0.3.1.dist-info/WHEEL
kwimage_ext-0.3.1.dist-info/top_level.txt
kwimage_ext-0.3.1.dist-info/RECORD
kwimage_ext-0.3.1.dist-info/licenses/LICENSE
